huaweicloudsdkcbr/__init__.py
huaweicloudsdkcbr/v1/__init__.py
huaweicloudsdkcbr/v1/cbr_async_client.py
huaweicloudsdkcbr/v1/cbr_client.py
huaweicloudsdkcbr/v1/model/__init__.py
huaweicloudsdkcbr/v1/model/add_agent_path_request.py
huaweicloudsdkcbr/v1/model/add_agent_path_response.py
huaweicloudsdkcbr/v1/model/add_member_request.py
huaweicloudsdkcbr/v1/model/add_member_response.py
huaweicloudsdkcbr/v1/model/add_members_req.py
huaweicloudsdkcbr/v1/model/add_vault_resource_request.py
huaweicloudsdkcbr/v1/model/add_vault_resource_response.py
huaweicloudsdkcbr/v1/model/agent.py
huaweicloudsdkcbr/v1/model/agent_add_path_req.py
huaweicloudsdkcbr/v1/model/agent_register.py
huaweicloudsdkcbr/v1/model/agent_register_req.py
huaweicloudsdkcbr/v1/model/agent_remove_path_req.py
huaweicloudsdkcbr/v1/model/agent_update.py
huaweicloudsdkcbr/v1/model/agent_update_req.py
huaweicloudsdkcbr/v1/model/associate_vault_policy_request.py
huaweicloudsdkcbr/v1/model/associate_vault_policy_response.py
huaweicloudsdkcbr/v1/model/backup_extend_info.py
huaweicloudsdkcbr/v1/model/backup_replicate_req.py
huaweicloudsdkcbr/v1/model/backup_replicate_req_body.py
huaweicloudsdkcbr/v1/model/backup_replicate_resp_body.py
huaweicloudsdkcbr/v1/model/backup_resp.py
huaweicloudsdkcbr/v1/model/backup_restore.py
huaweicloudsdkcbr/v1/model/backup_restore_req.py
huaweicloudsdkcbr/v1/model/backup_restore_server_mapping.py
huaweicloudsdkcbr/v1/model/backup_sync.py
huaweicloudsdkcbr/v1/model/backup_sync_req.py
huaweicloudsdkcbr/v1/model/backup_sync_resp_body.py
huaweicloudsdkcbr/v1/model/backup_update.py
huaweicloudsdkcbr/v1/model/backup_update_req.py
huaweicloudsdkcbr/v1/model/batch_create_and_delete_vault_tags_request.py
huaweicloudsdkcbr/v1/model/batch_create_and_delete_vault_tags_response.py
huaweicloudsdkcbr/v1/model/batch_update_vault_request.py
huaweicloudsdkcbr/v1/model/batch_update_vault_request_body.py
huaweicloudsdkcbr/v1/model/batch_update_vault_response.py
huaweicloudsdkcbr/v1/model/billing.py
huaweicloudsdkcbr-3.1.184.dist-info/METADATA
huaweicloudsdkcbr-3.1.184.dist-info/WHEEL
huaweicloudsdkcbr-3.1.184.dist-info/licenses/LICENSE
huaweicloudsdkcbr-3.1.184.dist-info/RECORD
